mvulib/__init__.py
mvulib/mvulib.ctf
mvulib/algorithms/__init__.py
mvulib/algorithms/mvu.py
mvulib-3.0.dist-info/METADATA
mvulib-3.0.dist-info/WHEEL
mvulib-3.0.dist-info/top_level.txt
mvulib-3.0.dist-info/RECORD
