Metadata-Version: 2.1
Name: mvulib
Version: 3.0
Summary: A Python Interface to MATLAB implementation of Maximum Variance Unfolding (MVU) dimensionality reduction algorithm. MATLAB Runtime 24.1 installation is required.
Platform: Linux
Platform: Windows
Platform: macOS
